{
  "genre": "法務・コンプライアンス",
  "exam": "情報セキュリティマネジメント試験",
  "questions": [
    {
      "id": "sg_lw_001",
      "question": "個人情報保護における「利用目的の特定」の趣旨として適切なものはどれか。",
      "choices": [
        "何のために個人情報を使うかを明確にする",
        "利用目的は担当者の裁量に任せる",
        "一度取得した情報は自由に利用する",
        "目的外利用の説明は不要である"
      ],
      "answer": 0,
      "explanation": "目的の明確化は適正取扱いの基本。"
    },
    {
      "id": "sg_lw_002",
      "question": "営業秘密に該当する情報の要件として適切なものはどれか。",
      "choices": [
        "秘密管理性・有用性・非公然性を満たす",
        "社内にある全情報が自動的に該当する",
        "一度公開された情報でも常に該当する",
        "口頭で伝えたものは該当しない"
      ],
      "answer": 0,
      "explanation": "不正競争防止法で定義される要件。"
    },
    {
      "id": "sg_lw_003",
      "question": "著作権の説明として適切なものはどれか。",
      "choices": [
        "プログラムや文章など創作物の表現を保護する",
        "アルゴリズムのアイデア自体を無期間で保護する",
        "会社名のみを保護対象とする",
        "仕様書は著作権の対象外である"
      ],
      "answer": 0,
      "explanation": "著作権は表現を保護する権利。"
    },
    {
      "id": "sg_lw_004",
      "question": "不正アクセス行為禁止法に照らし、問題となる行為はどれか。",
      "choices": [
        "他人のID・パスワードを無断で使用する",
        "自分のIDで正規業務を行う",
        "パスワード変更を定期実施する",
        "ログイン失敗を報告する"
      ],
      "answer": 0,
      "explanation": "他人認証情報の不正使用は禁止される。"
    },
    {
      "id": "sg_lw_005",
      "question": "マイナンバーを含む特定個人情報の取扱いとして適切なものはどれか。",
      "choices": [
        "取扱い業務を明確にし、必要最小限で管理する",
        "便利のため会社全員に共有する",
        "業務終了後も無期間保管する",
        "持出し記録は不要とする"
      ],
      "answer": 0,
      "explanation": "特定個人情報は厳格な管理が求められる。"
    },
    {
      "id": "sg_lw_006",
      "question": "委託先が個人情報を取り扱う場合の委託元の対応として適切なものはどれか。",
      "choices": [
        "委託先の選定・契約・監督を行う",
        "委託後は委託先に全責任を移譲する",
        "取扱い実態の確認は禁止する",
        "再委託を自由に認める"
      ],
      "answer": 0,
      "explanation": "委託元にも監督責任がある。"
    },
    {
      "id": "sg_lw_007",
      "question": "情報セキュリティ事故発生時の法的対応として適切なものはどれか。",
      "choices": [
        "匿さず可能な限り速やかに事実確認と必要報告を行う",
        "外部通知を避けるため記録を残さない",
        "とりあえず証拠ログを削除する",
        "被害者への説明は必要ない"
      ],
      "answer": 0,
      "explanation": "報告・説明責任と証拠保全が重要。"
    },
    {
      "id": "sg_lw_008",
      "question": "ソフトウェアライセンス管理で適切な運用はどれか。",
      "choices": [
        "使用許諾条件と保有数を管理し、超過利用を避ける",
        "フリーソフトと同様にすべて自由コピーする",
        "退職者アカウントへの割当を維持する",
        "インストール履歴を記録しない"
      ],
      "answer": 0,
      "explanation": "ライセンス違反は法的リスクにつながる。"
    },
    {
      "id": "sg_lw_009",
      "question": "コンプライアンス教育の効果を高める方法として適切なものはどれか。",
      "choices": [
        "業務例に即した演習と定期的な復習を行う",
        "入社時の1回のみで十分とする",
        "試験結果は分析しない",
        "対象者を管理職に限定する"
      ],
      "answer": 0,
      "explanation": "実務に紐付く教育と継続実施が必要。"
    },
    {
      "id": "sg_lw_010",
      "question": "ガイドライン等の改訂に対する組織の対応として適切なものはどれか。",
      "choices": [
        "影響分析を行い、規程・手順・教育を更新する",
        "一度定めた規程は改訂しない",
        "現場判断に任せて組織的見直しは不要",
        "新要求を私的チャットでのみ周知する"
      ],
      "answer": 0,
      "explanation": "法令・基準の変更は規程類と運用の更新が必要。"
    }
  ]
}